{"frameRate":30,"name":"FNY_R3","version":"5.5","compatibleVersion":"5.5","armature":[{"type":"Armature","frameRate":30,"name":"r3_arm","aabb":{"x":-195.29,"y":-143.65,"width":382.9,"height":323.45},"bone":[{"name":"r3_root"},{"length":260,"name":"box_root","parent":"r3_root","transform":{"x":3.4082,"y":0.7235,"scX":0.62,"scY":0.62}},{"length":260,"name":"box_","parent":"box_root"},{"name":"bone_ikTarget3","parent":"box_","transform":{"x":242.1697,"y":-103.6556,"scX":1.6129,"scY":1.6129}},{"length":96,"name":"box_bant_ik","parent":"box_","transform":{"x":122.1658,"y":-293.7291,"skX":-62.4081,"skY":-62.4081,"scX":1.6129,"scY":1.6129}},{"length":159,"name":"b_sparkles1","parent":"box_","transform":{"x":-6.9762,"y":-29.9895,"skX":180,"skY":180,"scX":1.6129,"scY":1.6129}},{"length":116,"name":"box_centerglow11","parent":"box_","transform":{"x":-0.9673,"y":-2.3144,"skX":1.5781,"skY":1.5781,"scX":1.129,"scY":1.129}},{"name":"bone_ikTarget4","parent":"box_","transform":{"x":-92.3464,"y":-216.159,"scX":1.6129,"scY":1.6129}},{"length":142,"name":"box_cornerglow","parent":"box_","transform":{"x":-5.3833,"y":10.8564,"skX":112,"skY":112,"scX":1.61,"scY":2.61}},{"length":61,"name":"box_bant","parent":"box_","transform":{"x":1.1259,"y":-81.4234,"skX":-126.0794,"skY":-126.0794}},{"length":159,"name":"b_sparkles","parent":"box_","transform":{"x":-6.9762,"y":-29.9895,"skX":28.29,"skY":28.29,"scX":1.6129,"scY":1.6129}},{"length":113,"name":"box_bant_front","parent":"box_","transform":{"x":5.5759,"y":-67.9734,"skX":58.2837,"skY":58.2837}},{"length":89,"name":"box_bant1","parent":"box_","transform":{"x":17.3759,"y":-73.5734,"skX":-8.0636,"skY":-8.0636}},{"length":122,"name":"box_bant_front1","parent":"box_","transform":{"x":5.2759,"y":-68.2234,"skX":160.4589,"skY":160.4589}},{"length":120,"name":"box_bottom","parent":"box_","transform":{"x":-52.7536,"y":153.5289,"skX":-67.3742,"skY":-67.3742}},{"name":"bone_ikTarget2","parent":"box_bant_ik","transform":{"x":-226.0331,"y":113.1126,"skX":62.4081,"skY":62.4081}},{"length":108,"name":"box_glow","parent":"box_bottom","transform":{"x":146.3477,"y":-18.0039,"skX":89.64,"skY":89.64,"scX":1.31,"scY":1.31}},{"length":116,"name":"box_centerglow","parent":"box_bottom","transform":{"x":190.6763,"y":-23.3673,"skX":68.9524,"skY":68.9524,"scX":1.6129,"scY":1.6129}},{"name":"bone_ikTarget1","parent":"box_bant_ik","transform":{"x":-299.4778,"y":-125.1587,"skX":62.4081,"skY":62.4081}},{"length":116,"name":"box_centerglow1","parent":"box_centerglow","transform":{"scX":0.7,"scY":0.7}}],"slot":[{"blendMode":"add","name":"b_centerglow11","parent":"box_centerglow11","color":{"gM":0,"bM":63}},{"name":"box_bottom_back","parent":"box_bottom"},{"blendMode":"add","name":"b_centerglow","parent":"box_centerglow","color":{"gM":63,"bM":0}},{"blendMode":"add","name":"b_centerglow1","parent":"box_centerglow1","color":{"gM":95,"bM":34}},{"name":"box_bottom","parent":"box_bottom"},{"name":"box_top","parent":"box_"},{"name":"box__tape","parent":"box_bottom"},{"blendMode":"add","name":"box_glow","parent":"box_glow"},{"blendMode":"add","name":"b_cornerglow","parent":"box_cornerglow","color":{"gM":80,"bM":0}},{"name":"box_bant","parent":"box_bant1"},{"name":"box_bant_front","parent":"box_bant_front1"},{"blendMode":"add","name":"b_sparkles","parent":"b_sparkles"},{"blendMode":"add","name":"b_sparkles1","parent":"b_sparkles1"}],"ik":[{"name":"bone_ik10","bone":"box_bant","target":"bone_ikTarget4"},{"name":"bone_ik8","bone":"box_bant_front","target":"bone_ikTarget2"},{"name":"bone_ik9","bone":"box_bant1","target":"bone_ikTarget3"},{"name":"bone_ik7","bone":"box_bant_front1","target":"bone_ikTarget1"}],"skin":[{"slot":[{"name":"box_top","display":[{"type":"mesh","name":"fruit_5_lines_ NY_animate/box_top","width":321,"height":191,"vertices":[161.33,-18.12,135.28,33.18,-6.42,52.83,-132.97,-64.37,-117.82,-116.17,29.33,-120.82,14.35,-1.87],"uvs":[0.96589,0.59895,0.88474,0.86754,0.4433,0.97042,0.04907,0.35681,0.09626,0.0856,0.55467,0.06126,0.508,0.68403],"triangles":[6,1,0,5,6,0,6,2,1,4,3,6,4,6,5,3,2,6],"edges":[0,1,1,2,2,3,3,4,4,5,5,0],"userEdges":[]}]},{"name":"box__tape","display":[{"type":"mesh","name":"fruit_5_lines_ NY_animate/box__tape","width":289,"height":313,"vertices":[-86.93,-254.03,-29.81,-193.54,46.62,-206.39,92.25,-305.46,32.68,-381.42,-55.11,-364.46,17.3,-297.85],"uvs":[0,0.66379,0.3188,0.9755,0.74535,0.90846,1,0.39875,0.66782,0.0074,0.17457,0.09474,0.5813,0.43797],"triangles":[6,2,3,4,6,3,5,6,4,6,1,2,0,1,6,5,0,6],"weights":[1,14,1,1,14,1,1,14,1,1,2,1,1,2,1,1,2,1,1,2,1],"slotPose":[1,0,0,1,0,0],"bonePose":[14,0.23852,-0.572283,0.572283,0.23852,-24.95,-201.15,2,0.62,0,0,0.62,7.757224,-296.337931],"edges":[0,1,1,2,2,3,3,4,4,5,5,0],"userEdges":[]}]},{"name":"box_glow","display":[{"name":"fruit_5_lines_ NY_animate/box_glow","transform":{"x":-0.4,"y":-0.37,"scX":1.1,"scY":1.1}}]},{"name":"b_centerglow11","display":[{"name":"fruit_5_lines_ NY_animate/b_centerglow","transform":{"x":0.7,"y":4.79,"skX":-1.58,"skY":-1.58,"scX":1.85,"scY":1.85}}]},{"name":"b_cornerglow","display":[{"name":"fruit_5_lines_ NY_animate/b_cornerglow","transform":{"x":55.61,"y":5.15,"skX":91.23,"skY":91.23}}]},{"name":"box_bant","display":[{"type":"mesh","name":"fruit_5_lines_ NY_animate/box_bant","width":243,"height":149,"vertices":[14.16,-346.01,14.81,-377.05,11.52,-396.39,5.36,-410.71,-1.03,-413.22,-12.04,-413.22,-44.77,-386.28,-44.77,-368.68,-34.48,-353.27,-16.22,-342.48,2.07,-335.66,12.18,-336.31,34.84,-331.94,48.04,-323.79,62.58,-320.84,83.91,-320.84,105.89,-351.07,105.89,-365.82,91.63,-375.93,62.58,-379.46,43.64,-371.31,20.76,-355.47],"uvs":[0.39115,0.72752,0.39547,0.39161,0.37366,0.18221,0.33272,0.02718,0.29033,0,0.21728,0,0,0.29161,0,0.48221,0.06831,0.64899,0.18951,0.76577,0.31091,0.8396,0.37798,0.83255,0.5284,0.87987,0.61605,0.96812,0.71255,1,0.85412,1,1,0.67282,1,0.51309,0.90535,0.40369,0.71255,0.36544,0.58683,0.45369,0.43498,0.62517],"triangles":[18,15,16,18,16,17,20,14,19,19,14,15,19,15,18,20,13,14,20,12,13,21,12,20,21,0,12,0,11,12,9,10,0,10,11,0,7,8,1,6,7,1,2,6,1,8,9,1,9,0,1,5,6,2,3,4,2,4,5,2],"weights":[2,9,0.517534,12,0.482466,2,9,0.702763,12,0.297237,2,9,0.750159,12,0.249841,2,9,0.79894,12,0.20106,2,9,0.846774,12,0.153226,2,9,0.917671,12,0.082329,2,9,0.937113,12,0.062887,2,9,0.838568,12,0.161432,2,9,0.754696,12,0.245304,2,9,0.704684,12,0.295316,2,9,0.652597,12,0.347403,2,9,0.367531,12,0.632469,2,9,0.139622,12,0.860378,2,9,0.189225,12,0.810775,2,9,0.169069,12,0.830931,2,9,0.124357,12,0.875643,2,9,0.009583,12,0.990417,2,9,0.02501,12,0.97499,2,9,0.065799,12,0.934201,2,9,0.193496,12,0.806504,2,9,0.262029,12,0.737971,2,9,0.430162,12,0.569838],"slotPose":[1,0,0,1,0,0],"bonePose":[9,-0.365122,-0.501085,0.501085,-0.365122,8.455294,-346.820445,12,0.61387,-0.086969,0.086969,0.61387,18.530294,-341.953445],"edges":[0,1,1,2,2,3,3,4,4,5,5,6,6,7,7,8,8,9,9,10,10,11,11,12,12,13,13,14,14,15,15,16,16,17,17,18,18,19,19,20,20,21,21,0],"userEdges":[]}]},{"name":"b_centerglow","display":[{"name":"fruit_5_lines_ NY_animate/b_centerglow","transform":{"x":0.7,"y":4.79,"skX":-1.58,"skY":-1.58}}]},{"name":"box_bottom_back","display":[{"name":"fruit_5_lines_ NY_animate/box_bottom_back","transform":{"x":114.27,"y":-6.05,"skX":67.37,"skY":67.37}}]},{"name":"b_sparkles","display":[{"name":"fruit_5_lines_ NY_animate/b_sparkles","transform":{"x":-1.53,"y":12.72,"skX":-1.29,"skY":-1.29}}]},{"name":"b_centerglow1","display":[{"name":"fruit_5_lines_ NY_animate/b_centerglow","transform":{"x":0.7,"y":4.79,"skX":-1.58,"skY":-1.58}}]},{"name":"b_sparkles1","display":[{"name":"fruit_5_lines_ NY_animate/b_sparkles","transform":{"x":-1.53,"y":12.72,"skX":8.75,"skY":8.75,"scX":0.75,"scY":0.75}}]},{"name":"box_bant_front","display":[{"type":"mesh","name":"fruit_5_lines_ NY_animate/box_bant_front","width":265,"height":176,"vertices":[33.39,-343.85,57.89,-330.47,72.88,-293.34,73.6,-262.69,64.22,-250.15,47.52,-249.76,40.3,-267.7,22.26,-295.21,9.99,-324.91,-4.86,-332.4,-19.7,-341.23,-27.79,-322.62,-44.69,-302.84,-59.73,-275.57,-91.48,-293.82,-91.8,-307.46,-66.1,-344.5,-44.25,-356.74,0.99,-357.81,24.61,-354.55],"uvs":[0.76698,0.13494,0.91415,0.26278,1,0.60625,1,0.88722,0.94113,1,0.83943,1,0.79811,0.83409,0.69226,0.57813,0.62189,0.30341,0.53264,0.23153,0.44358,0.14744,0.3917,0.31619,0.28604,0.49375,0.19057,0.74034,0,0.56619,0,0.44119,0.1617,0.10739,0.29642,0,0.57189,0,0.71509,0.03494],"triangles":[6,4,3,1,7,2,7,6,2,6,3,2,6,5,4,8,7,0,0,7,1,19,8,0,18,9,8,18,8,19,10,9,18,17,10,18,17,11,10,17,16,11,16,12,11,16,15,12,14,13,12,15,14,12],"weights":[2,13,0.473348,11,0.526652,2,13,0.362437,11,0.637563,2,13,0.129449,11,0.870551,2,13,0.088341,11,0.911659,2,13,0.092455,11,0.907545,2,13,0.081881,11,0.918119,2,13,0.027266,11,0.972734,2,13,0.076705,11,0.923295,2,13,0.294573,11,0.705427,2,13,0.999912,11,0.000088,2,13,0.843259,11,0.156741,2,13,0.999292,11,0.000708,2,13,0.959743,11,0.040257,2,13,0.869655,11,0.130345,2,13,0.903977,11,0.096023,2,13,0.916664,11,0.083336,2,13,0.846763,11,0.153237,2,13,0.717627,11,0.282373,2,13,0.5086,11,0.4914,2,13,0.499967,11,0.500033],"slotPose":[1,0,0,1,0,0],"bonePose":[13,-0.579225,0.221129,-0.221129,-0.579225,11.028294,-338.636445,11,0.319657,0.531244,-0.531244,0.319657,11.214294,-338.481445],"edges":[0,1,1,2,2,3,3,4,4,5,5,6,6,7,7,8,8,9,9,10,10,11,11,12,12,13,13,14,14,15,15,16,16,17,17,18,18,19,19,0],"userEdges":[]}]},{"name":"box_bottom","display":[{"type":"mesh","name":"fruit_5_lines_ NY_animate/box_bottom","width":363,"height":251,"vertices":[-89.19,-257.23,-27.69,-192.63,55.2,-208.22,93.27,-286.22,15.06,-343.26,-68.36,-337.83,5.7,-271.85],"uvs":[0.10014,0.58008,0.37342,0.99522,0.74174,0.89502,0.91088,0.39382,0.56336,0.02729,0.1927,0.06215,0.52178,0.48614],"triangles":[6,2,3,4,6,3,6,1,2,5,6,4,0,1,6,5,0,6],"weights":[1,14,1,1,14,1,1,14,1,1,14,1,1,14,1,1,14,1,1,14,1],"slotPose":[1,0,0,1,0,0],"bonePose":[14,0.23852,-0.572283,0.572283,0.23852,-24.95,-201.15],"edges":[0,1,1,2,2,3,3,4,4,5,5,0],"userEdges":[]}]}]}],"animation":[{"duration":45,"playTimes":0,"name":"sym_r3_","bone":[{"name":"box_","translateFrame":[{"duration":24,"curve":[0.5,0,0.5,1]},{"duration":21,"curve":[0.5,0,0.5,1],"y":-34.62},{"duration":0}],"rotateFrame":[{"duration":12,"curve":[0.5,0,0.5,1]},{"duration":22,"curve":[0.5,0,0.5,1],"rotate":-6},{"duration":11,"curve":[0.5,0,0.5,1],"rotate":-29.22},{"duration":0}],"scaleFrame":[{"duration":10,"curve":[0.5,0,0.5,1]},{"duration":10,"curve":[0.5,0,0.5,1],"x":0.95,"y":0.95},{"duration":25,"curve":[0.5,0,0.5,1],"x":1.1,"y":1.1},{"duration":0}]},{"name":"box_bottom","translateFrame":[{"duration":20,"curve":[0.5,0,0.5,1]},{"duration":10,"curve":[0.5,0,0.5,1],"x":-9.95,"y":37.82},{"duration":15,"curve":[0.5,0,0.5,1],"x":-9.95,"y":37.82},{"duration":0}]},{"name":"box_bant_ik","translateFrame":[{"duration":20,"curve":[0.5,0,0.5,1]},{"duration":10,"curve":[0.5,0,0.5,1],"x":57.99,"y":-131.73},{"duration":15,"curve":[0.5,0,0.5,1],"x":59.07,"y":-147.01},{"duration":0}]},{"name":"box_centerglow","translateFrame":[{"duration":20,"curve":[0.5,0,0.5,1],"x":-69.13,"y":11.24},{"duration":25,"curve":[0.5,0,0.5,1]},{"duration":0,"x":-69.13,"y":11.24}],"rotateFrame":[{"duration":45,"tweenEasing":0,"rotate":-68.95},{"duration":0,"rotate":111.05}],"scaleFrame":[{"duration":20,"curve":[0.5,0,0.5,1],"x":0.25,"y":0.25},{"duration":25,"curve":[0.5,0,0.5,1]},{"duration":0,"x":0.25,"y":0.25}]},{"name":"box_centerglow1","rotateFrame":[{"duration":45,"tweenEasing":0,"rotate":-68.95},{"duration":0,"rotate":111.05}]},{"name":"box_cornerglow","translateFrame":[{"duration":10},{"duration":10,"curve":[0.5,0,0.5,1]},{"duration":25,"curve":[0.5,0,0.5,1],"x":4.33,"y":1.68},{"duration":0}],"rotateFrame":[{"duration":10},{"duration":10,"curve":[0.5,0,0.5,1],"rotate":9},{"duration":10,"curve":[0.5,0,0.5,1]},{"duration":15,"rotate":-11}],"scaleFrame":[{"duration":10},{"duration":10,"curve":[0.5,0,0.5,1]},{"duration":25,"curve":[0.5,0,0.5,1],"x":0.55,"y":1.02},{"duration":0}]},{"name":"b_sparkles","translateFrame":[{"duration":8,"x":-4.29,"y":31.26},{"duration":16,"curve":[0.5,0,0.5,1],"x":-4.29,"y":31.26},{"duration":21,"curve":[0.5,0,0.5,1],"x":-6.78,"y":28.99},{"duration":0,"x":-6.03,"y":34.25}],"rotateFrame":[{"duration":45,"curve":[0.5,0,0.5,1],"rotate":-13},{"duration":0,"rotate":7}],"scaleFrame":[{"duration":28,"curve":[0.5,0,0.5,1],"x":0.56,"y":0.56},{"duration":8,"curve":[0.5,0,0.5,1],"x":1.12,"y":1.12},{"duration":4,"curve":[0.5,0,0.5,1]},{"duration":5,"curve":[0.5,0,0.5,1],"x":1.12,"y":1.12},{"duration":0,"x":0.56,"y":0.56}]},{"name":"b_sparkles1","translateFrame":[{"duration":4,"x":-4.29,"y":31.26},{"duration":16,"curve":[0.5,0,0.5,1],"x":-18.81,"y":70.76},{"duration":20,"curve":[0.5,0,0.5,1],"x":-14.14,"y":81.71},{"duration":5,"x":-18.81,"y":70.76}],"rotateFrame":[{"duration":40,"curve":[0.5,0,0.5,1],"rotate":-13},{"duration":5,"rotate":7}],"scaleFrame":[{"duration":13,"curve":[0.5,0,0.5,1],"x":0.56,"y":0.56},{"duration":8,"curve":[0.5,0,0.5,1],"x":1.12,"y":1.12},{"duration":8,"curve":[0.5,0,0.5,1]},{"duration":11,"curve":[0.5,0,0.5,1],"x":1.12,"y":1.12},{"duration":5,"x":0.56,"y":0.56}]},{"name":"box_centerglow11","rotateFrame":[{"duration":45,"tweenEasing":0,"rotate":-68.95},{"duration":0,"rotate":111.05}],"scaleFrame":[{"duration":13,"tweenEasing":0,"x":0.01,"y":0.01},{"duration":21,"tweenEasing":0},{"duration":11,"tweenEasing":0},{"duration":0,"x":0.01,"y":0.01}]},{"name":"box_glow","translateFrame":[{"duration":14,"curve":[0.5,0,0.5,1],"x":12.55,"y":1.68},{"duration":18,"curve":[0.5,0,0.5,1],"x":16.02,"y":-2.93},{"duration":13,"curve":[0.5,0,0.5,1],"x":16.02,"y":-2.93},{"duration":0,"x":12.55,"y":1.68}],"scaleFrame":[{"duration":14,"curve":[0.5,0,0.5,1],"y":0.73},{"duration":18,"curve":[0.5,0,0.5,1]},{"duration":13,"curve":[0.5,0,0.5,1]},{"duration":0,"y":0.73}]}],"slot":[{"name":"b_centerglow","colorFrame":[{"duration":10,"curve":[0.5,0,0.5,1],"value":{"aM":0,"gM":38,"bM":0}},{"duration":20,"curve":[0.5,0,0.5,1],"value":{"gM":38,"bM":0}},{"duration":10,"curve":[0.5,0,0.5,1],"value":{"gM":38,"bM":0}},{"duration":5,"value":{"aM":0,"gM":38,"bM":0}}]},{"name":"b_centerglow1","colorFrame":[{"duration":20,"curve":[0.5,0,0.5,1],"value":{"aM":0,"gM":38,"bM":0}},{"duration":25,"value":{"gM":98,"bM":98}}]},{"name":"b_cornerglow","colorFrame":[{"duration":10,"value":{"aM":0,"gM":80,"bM":0}},{"duration":6,"curve":[0.5,0,0.5,1],"value":{"aM":0,"gM":80,"bM":0}},{"duration":9,"curve":[0.5,0,0.5,1],"value":{"bM":0}},{"duration":11,"curve":[0.5,0,0.5,1],"value":{"bM":0}},{"duration":9,"value":{"aM":0,"gM":80,"bM":0}}]},{"name":"b_sparkles","colorFrame":[{"duration":8,"value":{"aM":0,"gM":71,"bM":0}},{"duration":8,"curve":[0.5,0,0.5,1],"value":{"aM":0,"gM":71,"bM":0}},{"duration":21,"curve":[0.5,0,0.5,1]},{"duration":3,"curve":[0.5,0,0.5,1]},{"duration":5,"value":{"aM":0,"gM":71,"bM":0}}]},{"name":"b_sparkles1","colorFrame":[{"duration":4,"value":{"aM":0,"gM":71,"bM":0}},{"duration":14,"curve":[0.5,0,0.5,1],"value":{"aM":0,"gM":71,"bM":0}},{"duration":13,"curve":[0.5,0,0.5,1]},{"duration":9,"curve":[0.5,0,0.5,1]},{"duration":5,"value":{"aM":0,"gM":71,"bM":0}}]},{"name":"box_glow","colorFrame":[{"duration":10,"curve":[0.5,0,0.5,1],"value":{"aM":0}},{"duration":25,"curve":[0.5,0,0.5,1]},{"duration":10,"curve":[0.5,0,0.5,1]},{"duration":0,"value":{"aM":0}}]}],"ffd":[{"name":"fruit_5_lines_ NY_animate/box_bottom","slot":"box_bottom","frame":[{"duration":20,"curve":[0.5,0,0.5,1]},{"duration":25,"curve":[0.5,0,0.5,1],"offset":2,"vertices":[-6.29,13.39,0,0,0,0,15.41,-5.76,0,0,-6.29,13.39]},{"duration":0}]},{"name":"fruit_5_lines_ NY_animate/box_top","slot":"box_top","frame":[{"duration":20,"curve":[0.5,0,0.5,1]},{"duration":10,"curve":[0.5,0,0.5,1],"offset":4,"vertices":[13.74,-26.78,0,0,0,0,-7.2,23.5,13.74,-26.78]},{"duration":15,"curve":[0.5,0,0.5,1],"offset":4,"vertices":[17.19,-34.42,0,0,0,0,-10,33.77,19.68,-39.31]},{"duration":0}]},{"name":"fruit_5_lines_ NY_animate/box__tape","slot":"box__tape","frame":[{"duration":20,"curve":[0.5,0,0.5,1]},{"duration":10,"curve":[0.5,0,0.5,1],"offset":2,"vertices":[-6.91,18.43,0,0,8.01,-2.19,-4.01,14.63,0,0,6.83,-16.55]},{"duration":15,"tweenEasing":0,"offset":2,"vertices":[-5.51,14.68,0,0,6.38,-1.75,-4.05,22.31,0,0,11.32,-23.6]},{"duration":0}]}]}],"defaultActions":[{"gotoAndPlay":"sym_r3_"}],"canvas":{"width":350,"height":350}}]}